simpletrainer/__init__.py
simpletrainer/base_trainer.py
simpletrainer/criteria.py
simpletrainer/metrics.py
simpletrainer/optimizers.py
simpletrainer/schedulers.py
simpletrainer/utils.py
torch_simpletrainer-0.1.1.dist-info/METADATA
torch_simpletrainer-0.1.1.dist-info/WHEEL
torch_simpletrainer-0.1.1.dist-info/top_level.txt
torch_simpletrainer-0.1.1.dist-info/RECORD
