Metadata-Version: 2.4
Name: torch-simpletrainer
Version: 0.1.1
Summary: A simple, flexible training framework for PyTorch models.
Author: Raha Ahmadi
License: MIT
Project-URL: Homepage, https://github.com/rahaahmadi/simpletrainer.git
Project-URL: Repository, https://github.com/rahaahmadi/simpletrainer.git
Project-URL: Issues, https://github.com/rahaahmadi/simpletrainer/issues
Keywords: pytorch,trainer,training,deep-learning,machine-learning
Classifier: Development Status :: 3 - Alpha
Classifier: Intended Audience :: Science/Research
Classifier: License :: OSI Approved :: MIT License
Classifier: Programming Language :: Python :: 3
Classifier: Topic :: Scientific/Engineering :: Artificial Intelligence
Requires-Python: >=3.8
Requires-Dist: numpy
Requires-Dist: scikit-learn
Provides-Extra: torch
Requires-Dist: torch>=2.0; extra == "torch"
Provides-Extra: wandb
Requires-Dist: wandb>=0.13; extra == "wandb"
